beeoptimal/__init__.py
beeoptimal/abc.py
beeoptimal/bee.py
beeoptimal/benchmarks.py
beeoptimal/plotting.py
beeoptimal/utils.py
beeoptimal/package_assets/BeeMarker.png
beeoptimal-0.1.1.dist-info/LICENSE
beeoptimal-0.1.1.dist-info/METADATA
beeoptimal-0.1.1.dist-info/WHEEL
beeoptimal-0.1.1.dist-info/top_level.txt
beeoptimal-0.1.1.dist-info/RECORD
