Metadata-Version: 2.1
Name: beeoptimal
Version: 0.1.1
Summary: A Python implementation of the Artificial Bee Colony (ABC) optimization algorithm
Author-email: Giulio Fantuzzi <giulio.fantuzzi01@gmail.com>
License: MIT License
Project-URL: Documentation, https://beeoptimal.readthedocs.io/en/latest/
Project-URL: Repository, https://github.com/giuliofantuzzi/BeeOptimal
Project-URL: Issues, https://github.com/giuliofantuzzi/BeeOptimal/issues
Keywords: metahueristic,optimization,artificial bee colony,swarm intelligence
Classifier: Programming Language :: Python :: 3.12
Classifier: License :: OSI Approved :: MIT License
Classifier: Operating System :: OS Independent
Requires-Python: >=3.12.1
License-File: LICENSE
Requires-Dist: numpy<2.0.0,>=1.26.4
Requires-Dist: plotly>=5.24.1
Requires-Dist: tqdm>=4.66.4
Requires-Dist: pillow>=10.3.0
Requires-Dist: kaleido>=0.2.1
Provides-Extra: docs
Requires-Dist: sphinx>=4.0.0; extra == "docs"
Requires-Dist: sphinx-rtd-theme; extra == "docs"
Requires-Dist: nbsphinx; extra == "docs"
Requires-Dist: nbsphinx-link; extra == "docs"
Requires-Dist: sphinx-rtd-dark-mode; extra == "docs"
Provides-Extra: tutorials
Requires-Dist: ipython>=8.12.3; extra == "tutorials"
Requires-Dist: torchvision>=0.18.1; extra == "tutorials"
Requires-Dist: matplotlib>=3.8.4; extra == "tutorials"
